pystog/__init__.py
pystog/_version.py
pystog/cli.py
pystog/converter.py
pystog/fourier_filter.py
pystog/io.py
pystog/stog.py
pystog/transformer.py
pystog/utils.py
tests/__init__.py
tests/create_test_files.py
tests/materials.py
tests/runner.py
tests/test_converter.py
tests/test_fourier_filter.py
tests/test_stog.py
tests/test_transformer.py
tests/utils.py
tests/test_data/__init__.py
tests/test_data/argon.gr
tests/test_data/argon.real_space.dat
tests/test_data/argon.reciprocal_space.dat
tests/test_data/nickel.gr
tests/test_data/nickel.real_space.dat
tests/test_data/nickel.reciprocal_space.dat
pystog-1.0.0.dist-info/LICENSE
pystog-1.0.0.dist-info/METADATA
pystog-1.0.0.dist-info/WHEEL
pystog-1.0.0.dist-info/entry_points.txt
pystog-1.0.0.dist-info/top_level.txt
pystog-1.0.0.dist-info/RECORD
