Metadata-Version: 2.1
Name: pystog
Version: 1.0.0
Summary: Manipulate total scattering functions
Home-page: https://github.com/neutrons/pystog
Author: Marshall McDonnell (marshallmcdonnell),Mathieu Doucet (mdoucet),Ross Whitfield (rosswhitfield),Pete Peterson (peterfpeterson),Yuanpeng Zhang (Kvieta1990)
Author-email: mcdonnellmt@ornl.gov
License: GPL License (version 3)
Platform: UNKNOWN
Classifier: Programming Language :: Python :: 3
Classifier: License :: OSI Approved :: GNU General Public License v3 (GPLv3)
Classifier: Operating System :: OS Independent
Requires-Dist: matplotlib (==3.3.3)
Requires-Dist: numpy (==1.19.4)
Requires-Dist: pandas (>=1.1)
